rosewater.py
rosewater-0.1.1.dist-info/LICENSE
rosewater-0.1.1.dist-info/METADATA
rosewater-0.1.1.dist-info/WHEEL
rosewater-0.1.1.dist-info/entry_points.txt
rosewater-0.1.1.dist-info/top_level.txt
rosewater-0.1.1.dist-info/RECORD
