Metadata-Version: 2.1
Name: rosewater
Version: 0.1.1
Summary: Expression-aware gene assignment of ROSE output.
Home-page: https://github.com/j-andrews7/rosewater
Author: Jared Andrews
Author-email: jared.andrews07@gmail.com
License: UNKNOWN
Platform: UNKNOWN
Classifier: License :: OSI Approved :: GNU General Public License v3 (GPLv3)
Classifier: Programming Language :: Python :: 3
Classifier: Topic :: Scientific/Engineering :: Bio-Informatics
Classifier: Development Status :: 4 - Beta
Requires-Python: >=3
Requires-Dist: Click
Requires-Dist: pandas
Requires-Dist: pybedtools
